basedflare_session/__init__.py
basedflare_session/exceptions.py
basedflare_session/session.py
basedflare_session/utils.py
basedflare_session-0.1.1.dist-info/LICENSE
basedflare_session-0.1.1.dist-info/METADATA
basedflare_session-0.1.1.dist-info/WHEEL
basedflare_session-0.1.1.dist-info/top_level.txt
basedflare_session-0.1.1.dist-info/RECORD
