Metadata-Version: 2.1
Name: basedflare-session
Version: 0.1.1
Summary: Provides a requests-flavored session to solve BasedFlare challenges automatically. It also includes utility functions to solve the challenges manually.
Author-email: loynet <loynet@protonmail.com>
License: GNU AFFERO GENERAL PUBLIC LICENSE
Project-URL: Homepage, https://github.com/loynet/basedflare-session
Project-URL: Issues, https://github.com/loynet/basedflare-session/issues
Project-URL: Repository, https://github.com/loynet/basedflare-session.git
Keywords: basedflare,session
Classifier: Development Status :: 3 - Alpha
Classifier: Programming Language :: Python :: 3
Classifier: Intended Audience :: Developers
Requires-Python: >=3.8
License-File: LICENSE
Requires-Dist: requests >=2.31.0
Requires-Dist: argon2-cffi >=23.1.0
